octranspo/__init__.py
octranspo/data.py
octranspo/error.py
octranspo/octranspo.py
octranspo-0.1.0.dist-info/LICENSE-APACHE
octranspo-0.1.0.dist-info/LICENSE-MIT
octranspo-0.1.0.dist-info/METADATA
octranspo-0.1.0.dist-info/WHEEL
octranspo-0.1.0.dist-info/top_level.txt
octranspo-0.1.0.dist-info/RECORD
