Metadata-Version: 2.1
Name: octranspo
Version: 0.1.0
Summary: A Python wrapper around the OC Transpo API.
Home-page: https://gitlab.com/MysteryBlokHed/greasetools
Author: Adam Thompson-Sharpe
Author-email: adamthompsonsharpe@gmail.com
License: UNKNOWN
Platform: UNKNOWN
Classifier: Intended Audience :: End Users/Desktop
Classifier: License :: OSI Approved :: Apache Software License
Classifier: License :: OSI Approved :: MIT License
Classifier: Natural Language :: English
Classifier: Operating System :: OS Independent
Classifier: Programming Language :: Python
Classifier: Programming Language :: Python :: 3
Classifier: Programming Language :: Python :: 3.8
Classifier: Programming Language :: Python :: 3.9
Classifier: Programming Language :: Python :: 3.10
Requires-Python: ~=3.8
License-File: LICENSE-APACHE
License-File: LICENSE-MIT
Requires-Dist: requests (~=2.25)
